{
  "version": "7",
  "dialect": "postgresql",
  "entries": [
    {
      "idx": 0,
      "version": "7",
      "when": 1773505239606,
      "tag": "0000_neat_microchip",
      "breakpoints": true
    },
    {
      "idx": 1,
      "version": "7",
      "when": 1773516027011,
      "tag": "0001_fix-claims-estimated-loss",
      "breakpoints": true
    },
    {
      "idx": 2,
      "version": "7",
      "when": 1773674069665,
      "tag": "0002_ordinary_fixer",
      "breakpoints": true
    }
  ]
}